pipcolouringslibV1/__init__.py
pipcolouringslibV1-1.5.1.dist-info/METADATA
pipcolouringslibV1-1.5.1.dist-info/WHEEL
pipcolouringslibV1-1.5.1.dist-info/top_level.txt
pipcolouringslibV1-1.5.1.dist-info/RECORD
